camel_tools/VERSION
camel_tools/__init__.py
camel_tools/cli/__init__.py
camel_tools/cli/camel_arclean.py
camel_tools/cli/camel_data.py
camel_tools/cli/camel_dediac.py
camel_tools/cli/camel_diac.py
camel_tools/cli/camel_morphology.py
camel_tools/cli/camel_transliterate.py
camel_tools/cli/camel_word_tokenize.py
camel_tools/cli/utils.py
camel_tools/data/__init__.py
camel_tools/data/catalogue.py
camel_tools/data/downloader.py
camel_tools/data/post_install.py
camel_tools/dialectid/__init__.py
camel_tools/dialectid/common.py
camel_tools/dialectid/model26.py
camel_tools/dialectid/model6.py
camel_tools/disambig/__init__.py
camel_tools/disambig/common.py
camel_tools/disambig/mle.py
camel_tools/disambig/score_function.py
camel_tools/disambig/bert/__init__.py
camel_tools/disambig/bert/_bert_morph_dataset.py
camel_tools/disambig/bert/unfactored.py
camel_tools/morphology/__init__.py
camel_tools/morphology/analyzer.py
camel_tools/morphology/database.py
camel_tools/morphology/errors.py
camel_tools/morphology/generator.py
camel_tools/morphology/reinflector.py
camel_tools/morphology/utils.py
camel_tools/ner/__init__.py
camel_tools/sentiment/__init__.py
camel_tools/tagger/__init__.py
camel_tools/tagger/common.py
camel_tools/tagger/default.py
camel_tools/tokenizers/__init__.py
camel_tools/tokenizers/morphological.py
camel_tools/tokenizers/word.py
camel_tools/utils/__init__.py
camel_tools/utils/charmap.py
camel_tools/utils/charsets.py
camel_tools/utils/dediac.py
camel_tools/utils/normalize.py
camel_tools/utils/stringutils.py
camel_tools/utils/transliterate.py
camel_tools/utils/charmaps/ar2bw_map.json
camel_tools/utils/charmaps/ar2hsb_map.json
camel_tools/utils/charmaps/ar2safebw_map.json
camel_tools/utils/charmaps/ar2xmlbw_map.json
camel_tools/utils/charmaps/arclean_map.json
camel_tools/utils/charmaps/bw2ar_map.json
camel_tools/utils/charmaps/bw2hsb_map.json
camel_tools/utils/charmaps/bw2safebw_map.json
camel_tools/utils/charmaps/bw2xmlbw_map.json
camel_tools-1.5.7.dist-info/licenses/LICENSE
camel_tools-1.5.7.dist-info/METADATA
camel_tools-1.5.7.dist-info/WHEEL
camel_tools-1.5.7.dist-info/entry_points.txt
camel_tools-1.5.7.dist-info/top_level.txt
camel_tools-1.5.7.dist-info/RECORD
