Metadata-Version: 2.4
Name: camel_tools
Version: 1.5.7
Summary: A suite of Arabic natural language processing tools developed by the CAMeL Lab at New York University Abu Dhabi.
Home-page: https://github.com/CAMeL-Lab/CAMeL_Tools
Author: Ossama W. Obeid
Author-email: oobeid@nyu.edu
Maintainer: Ossama W. Obeid
Maintainer-email: oobeid@nyu.edu
License: MIT
Classifier: Development Status :: 5 - Production/Stable
Classifier: Environment :: Console
Classifier: Intended Audience :: Developers
Classifier: Intended Audience :: Education
Classifier: Intended Audience :: Information Technology
Classifier: Intended Audience :: Science/Research
Classifier: License :: OSI Approved :: MIT License
Classifier: Natural Language :: Arabic
Classifier: Operating System :: OS Independent
Classifier: Programming Language :: Python :: 3
Classifier: Programming Language :: Python :: 3 :: Only
Classifier: Programming Language :: Python :: 3.8
Classifier: Programming Language :: Python :: 3.9
Classifier: Programming Language :: Python :: 3.10
Classifier: Programming Language :: Python :: 3.11
Classifier: Programming Language :: Python :: 3.12
Classifier: Topic :: Scientific/Engineering
Classifier: Topic :: Scientific/Engineering :: Artificial Intelligence
Classifier: Topic :: Scientific/Engineering :: Information Analysis
Classifier: Topic :: Text Processing
Classifier: Topic :: Text Processing :: Linguistic
Requires-Python: >=3.8.0, <3.13
License-File: LICENSE
Requires-Dist: future
Requires-Dist: six
Requires-Dist: docopt
Requires-Dist: cachetools<=6.0.0
Requires-Dist: numpy<2
Requires-Dist: scipy
Requires-Dist: pandas
Requires-Dist: scikit-learn
Requires-Dist: dill
Requires-Dist: torch>=2.0
Requires-Dist: transformers<4.44.0,>=4.0
Requires-Dist: editdistance
Requires-Dist: requests
Requires-Dist: emoji
Requires-Dist: pyrsistent
Requires-Dist: tabulate
Requires-Dist: tqdm
Requires-Dist: muddler
Requires-Dist: camel-kenlm<=2025.09.16; platform_system != "Windows"
Dynamic: author
Dynamic: author-email
Dynamic: classifier
Dynamic: description
Dynamic: home-page
Dynamic: license
Dynamic: license-file
Dynamic: maintainer
Dynamic: maintainer-email
Dynamic: requires-dist
Dynamic: requires-python
Dynamic: summary
